{
  "metadata": {
    "scraped_at": "2026-06-09T22:47:48.041415+00:00",
    "category": "OVERALL",
    "time_period": "ALL",
    "activity_filter_hours": 24,
    "total_wallets": 32,
    "enriched_wallets": 32,
    "leaderboard_pulled": 100,
    "active_after_filter": 32
  },
  "wallets": [
    {
      "rank": "29",
      "proxyWallet": "0xbddf61af533ff524d27154e589d2d7a81510c684",
      "userName": "Countryside",
      "profileImage": "",
      "xUsername": "",
      "verifiedBadge": false,
      "pnl": 3533782.6298831967,
      "vol": 415178706.305459,
      "enriched": {
        "winRate": 80.8,
        "roi": 67.5,
        "totalTrades": 250,
        "wins": 202,
        "losses": 48,
        "categories": [
          "Geopolitics",
          "Sports"
        ],
        "sharpe": 0.41,
        "consistency": 88.0,
        "maxDrawdown": -470003.39,
        "sparkline": [
          37834.7,
          38555.17,
          38600.92,
          162884.6,
          162997.44,
          165705.05,
          179590.76,
          222913.03,
          306542.83
        ],
        "openPositions": 50,
        "closedPositions": 250,
        "hasCrypto": false,
        "totalPnlFromPositions": 10254751.89,
        "totalInvested": 15183849.17,
        "lastTradeTimestamp": 1781044834,
        "tradesInWindow": 50,
        "lastTradeAge": "0.1h ago"
      },
      "scoredRank": 1
    },
    {
      "rank": "65",
      "proxyWallet": "0xea2b4224411e723499a803ce3f4758779fb31fc6",
      "userName": "frankfrankfrank",
      "profileImage": "",
      "xUsername": "",
      "verifiedBadge": false,
      "pnl": 1771260.82096111,
      "vol": 41760935.825917,
      "enriched": {
        "winRate": 80.0,
        "roi": 58.9,
        "totalTrades": 250,
        "wins": 200,
        "losses": 50,
        "categories": [
          "Crypto",
          "Finance",
          "Geopolitics",
          "Sports",
          "Tech",
          "Weather"
        ],
        "sharpe": 0.37,
        "consistency": 88.0,
        "maxDrawdown": -63558.56,
        "sparkline": [
          895.65,
          24095.65,
          24193.25,
          89181.03,
          94434.91,
          95257.15,
          117727.05,
          114976.58,
          72550.05
        ],
        "openPositions": 50,
        "closedPositions": 250,
        "hasCrypto": true,
        "totalPnlFromPositions": 3210119.23,
        "totalInvested": 5447115.62,
        "lastTradeTimestamp": 1781022060,
        "tradesInWindow": 34,
        "lastTradeAge": "6.4h ago"
      },
      "scoredRank": 2
    },
    {
      "rank": "33",
      "proxyWallet": "0x9d84ce0306f8551e02efef1680475fc0f1dc1344",
      "userName": "ImJustKen",
      "profileImage": "https://polymarket-upload.s3.us-east-2.amazonaws.com/profile-image-82662-8ddbc8e8-0500-44b7-bb13-c0b32a40a45d.jpg",
      "xUsername": "Domahhhh",
      "verifiedBadge": true,
      "pnl": 3118979.6493634456,
      "vol": 475965935.413632,
      "enriched": {
        "winRate": 67.2,
        "roi": 44.5,
        "totalTrades": 250,
        "wins": 168,
        "losses": 82,
        "categories": [
          "Crypto",
          "Culture",
          "Economics",
          "Finance",
          "Geopolitics",
          "Politics",
          "Sports",
          "Tech",
          "Weather"
        ],
        "sharpe": 0.07,
        "consistency": 80.0,
        "maxDrawdown": -23701.09,
        "sparkline": [
          311.23,
          133.63,
          -88.36,
          -332.56,
          -167.64,
          -215.09,
          765.08,
          1009.24,
          2087.96
        ],
        "openPositions": 50,
        "closedPositions": 250,
        "hasCrypto": true,
        "totalPnlFromPositions": 1665383.82,
        "totalInvested": 3745951.89,
        "lastTradeTimestamp": 1781021571,
        "tradesInWindow": 50,
        "lastTradeAge": "6.5h ago"
      },
      "scoredRank": 3
    },
    {
      "rank": "61",
      "proxyWallet": "0xed107a85a4585a381e48c7f7ca4144909e7dd2e5",
      "userName": "elmcap2",
      "profileImage": "https://polymarket-upload.s3.us-east-2.amazonaws.com/profile-image-117964-17fe5149-f238-4d6e-8b47-49fee9159b3e.png",
      "xUsername": "elm_cap",
      "verifiedBadge": false,
      "pnl": 1916503.5001232564,
      "vol": 247189313.02182397,
      "enriched": {
        "winRate": 88.0,
        "roi": 0.4,
        "totalTrades": 250,
        "wins": 220,
        "losses": 30,
        "categories": [
          "Crypto",
          "Culture",
          "Economics",
          "Finance",
          "Geopolitics",
          "Politics",
          "Sports",
          "Tech"
        ],
        "sharpe": 0.19,
        "consistency": 92.0,
        "maxDrawdown": -11168.48,
        "sparkline": [
          50.0,
          139.25,
          481.57,
          496.57,
          873.97,
          889.07,
          1456.74,
          11228.65,
          11228.65
        ],
        "openPositions": 50,
        "closedPositions": 250,
        "hasCrypto": true,
        "totalPnlFromPositions": 203507.16,
        "totalInvested": 49905672.02,
        "lastTradeTimestamp": 1781044872,
        "tradesInWindow": 50,
        "lastTradeAge": "0.1h ago"
      },
      "scoredRank": 4
    },
    {
      "rank": "68",
      "proxyWallet": "0xcc500cbcc8b7cf5bd21975ebbea34f21b5644c82",
      "userName": "justdance",
      "profileImage": "https://polymarket-upload.s3.us-east-2.amazonaws.com/profile-image-508970.png",
      "xUsername": "",
      "verifiedBadge": false,
      "pnl": 1742726.2368957696,
      "vol": 109649184.80964902,
      "enriched": {
        "winRate": 78.8,
        "roi": 11.7,
        "totalTrades": 250,
        "wins": 197,
        "losses": 53,
        "categories": [
          "Crypto"
        ],
        "sharpe": 0.1,
        "consistency": 81.0,
        "maxDrawdown": -32324.45,
        "sparkline": [
          -87.4,
          -85.4,
          39.33,
          110.73,
          217.07,
          6121.08,
          6201.97,
          6490.05,
          6490.64
        ],
        "openPositions": 50,
        "closedPositions": 250,
        "hasCrypto": true,
        "totalPnlFromPositions": 105443.39,
        "totalInvested": 901767.74,
        "lastTradeTimestamp": 1781044996,
        "tradesInWindow": 50,
        "lastTradeAge": "0.1h ago"
      },
      "scoredRank": 5
    },
    {
      "rank": "67",
      "proxyWallet": "0xb91aeb5accc33a5f9a8615b8ed6b2d352e913987",
      "userName": "afghj2421",
      "profileImage": "",
      "xUsername": "",
      "verifiedBadge": false,
      "pnl": 1747462.3591388236,
      "vol": 14554043.101471,
      "enriched": {
        "winRate": 60.2,
        "roi": 24.4,
        "totalTrades": 123,
        "wins": 74,
        "losses": 49,
        "categories": [
          "Sports"
        ],
        "sharpe": 0.2,
        "consistency": 74.0,
        "maxDrawdown": -141668.56,
        "sparkline": [
          49872.52,
          -561.0,
          11169.74,
          140144.57,
          239280.75,
          339343.15,
          268415.92,
          154206.34,
          217354.25
        ],
        "openPositions": 3,
        "closedPositions": 123,
        "hasCrypto": false,
        "totalPnlFromPositions": 1745482.93,
        "totalInvested": 7149928.01,
        "lastTradeTimestamp": 1781044906,
        "tradesInWindow": 50,
        "lastTradeAge": "0.1h ago"
      },
      "scoredRank": 6
    },
    {
      "rank": "91",
      "proxyWallet": "0xb6d6e99d3bfe055874a04279f659f009fd57be17",
      "userName": "JPMorgan101",
      "profileImage": "",
      "xUsername": "",
      "verifiedBadge": false,
      "pnl": 1352534.5829312715,
      "vol": 18979733.747839,
      "enriched": {
        "winRate": 65.2,
        "roi": 50.3,
        "totalTrades": 250,
        "wins": 163,
        "losses": 87,
        "categories": [
          "Crypto",
          "Finance",
          "Geopolitics",
          "Sports",
          "Tech",
          "Weather"
        ],
        "sharpe": 0.25,
        "consistency": 79.0,
        "maxDrawdown": -61508.59,
        "sparkline": [
          166542.6,
          167717.04,
          168178.8,
          168178.8,
          168179.18,
          168181.66,
          168152.68,
          168123.76,
          168142.43
        ],
        "openPositions": 50,
        "closedPositions": 250,
        "hasCrypto": true,
        "totalPnlFromPositions": 3209541.49,
        "totalInvested": 6377977.02,
        "lastTradeTimestamp": 1780965009,
        "tradesInWindow": 1,
        "lastTradeAge": "22.3h ago"
      },
      "scoredRank": 7
    },
    {
      "rank": "96",
      "proxyWallet": "0x6bab41a0dc40d6dd4c1a915b8c01969479fd1292",
      "userName": "Dropper",
      "profileImage": "https://polymarket-upload.s3.us-east-2.amazonaws.com/images_0a57a0c2-437f-41be-9ab8-5376ab6f3ca7_1726693550341.jpeg",
      "xUsername": "DropperPM",
      "verifiedBadge": false,
      "pnl": 1294973.1128941204,
      "vol": 48541089.768952996,
      "enriched": {
        "winRate": 67.6,
        "roi": 9.0,
        "totalTrades": 250,
        "wins": 169,
        "losses": 81,
        "categories": [
          "Crypto",
          "Culture",
          "Economics",
          "Finance",
          "Geopolitics",
          "Politics",
          "Sports",
          "Tech",
          "Weather"
        ],
        "sharpe": 0.17,
        "consistency": 78.0,
        "maxDrawdown": -97735.24,
        "sparkline": [
          22500.0,
          20514.14,
          21467.25,
          16613.24,
          12689.16,
          10863.4,
          9752.4,
          9835.01,
          13984.47
        ],
        "openPositions": 41,
        "closedPositions": 250,
        "hasCrypto": true,
        "totalPnlFromPositions": 800570.4,
        "totalInvested": 8880885.71,
        "lastTradeTimestamp": 1781042872,
        "tradesInWindow": 50,
        "lastTradeAge": "0.7h ago"
      },
      "scoredRank": 8
    },
    {
      "rank": "54",
      "proxyWallet": "0x2c335066fe58fe9237c3d3dc7b275c2a034a0563",
      "userName": "0x2c335066FE58fe9237c3d3Dc7b275C2a034a0563-1759935795465",
      "profileImage": "",
      "xUsername": "",
      "verifiedBadge": false,
      "pnl": 2022721.8432762688,
      "vol": 154272551.91229498,
      "enriched": {
        "winRate": 74.8,
        "roi": 6.1,
        "totalTrades": 250,
        "wins": 187,
        "losses": 63,
        "categories": [
          "Crypto",
          "Economics",
          "Geopolitics",
          "Sports",
          "Tech",
          "Weather"
        ],
        "sharpe": 0.08,
        "consistency": 79.0,
        "maxDrawdown": -402503.27,
        "sparkline": [
          4202.37,
          4547.96,
          -14666.33,
          -108694.62,
          -102182.21,
          -102173.53,
          -92103.19,
          -90942.93,
          -90073.49
        ],
        "openPositions": 50,
        "closedPositions": 250,
        "hasCrypto": true,
        "totalPnlFromPositions": 1390299.13,
        "totalInvested": 22682167.91,
        "lastTradeTimestamp": 1781044798,
        "tradesInWindow": 50,
        "lastTradeAge": "0.1h ago"
      },
      "scoredRank": 9
    },
    {
      "rank": "53",
      "proxyWallet": "0x44c1dfe43260c94ed4f1d00de2e1f80fb113ebc1",
      "userName": "aenews2",
      "profileImage": "https://polymarket-upload.s3.us-east-2.amazonaws.com/profile-image-154436-a84dabd0-06ee-40d3-be95-e454283cdfc0.jpg",
      "xUsername": "aenews",
      "verifiedBadge": false,
      "pnl": 2031117.900935182,
      "vol": 228967160.13830703,
      "enriched": {
        "winRate": 70.4,
        "roi": 9.2,
        "totalTrades": 250,
        "wins": 176,
        "losses": 74,
        "categories": [
          "Crypto",
          "Culture",
          "Economics",
          "Finance",
          "Geopolitics",
          "Politics",
          "Sports",
          "Tech",
          "Weather"
        ],
        "sharpe": 0.08,
        "consistency": 78.0,
        "maxDrawdown": -87289.57,
        "sparkline": [
          -100.0,
          -1481.16,
          -1458.46,
          -5439.56,
          -58996.91,
          -58940.49,
          -63071.35,
          -63024.16,
          -62721.58
        ],
        "openPositions": 50,
        "closedPositions": 250,
        "hasCrypto": true,
        "totalPnlFromPositions": 453090.0,
        "totalInvested": 4913518.31,
        "lastTradeTimestamp": 1781044648,
        "tradesInWindow": 50,
        "lastTradeAge": "0.1h ago"
      },
      "scoredRank": 10
    },
    {
      "rank": "47",
      "proxyWallet": "0x03e8a544e97eeff5753bc1e90d46e5ef22af1697",
      "userName": "weflyhigh",
      "profileImage": "",
      "xUsername": "",
      "verifiedBadge": false,
      "pnl": 2293045.15003209,
      "vol": 124809990.1341,
      "enriched": {
        "winRate": 42.8,
        "roi": 29.8,
        "totalTrades": 250,
        "wins": 107,
        "losses": 143,
        "categories": [
          "Crypto",
          "Culture",
          "Finance",
          "Geopolitics",
          "Sports",
          "Weather"
        ],
        "sharpe": 0.24,
        "consistency": 64.0,
        "maxDrawdown": -368252.21,
        "sparkline": [
          203999.89,
          226231.71,
          366314.3,
          391379.03,
          436937.44,
          444498.98,
          444471.48,
          440724.71,
          426624.76
        ],
        "openPositions": 31,
        "closedPositions": 250,
        "hasCrypto": true,
        "totalPnlFromPositions": 4782703.09,
        "totalInvested": 16045129.02,
        "lastTradeTimestamp": 1781044837,
        "tradesInWindow": 50,
        "lastTradeAge": "0.1h ago"
      },
      "scoredRank": 11
    },
    {
      "rank": "87",
      "proxyWallet": "0xd1acd3925d895de9aec98ff95f3a30c5279d08d5",
      "userName": "Kickstand7",
      "profileImage": "https://polymarket-upload.s3.us-east-2.amazonaws.com/0x47bc4b50a8d0c4a07b22bfd949f9c6afb8aec043_c396c188-aff2-47b3-bf31-b7ea4a6a7ff2_1721230013186.png",
      "xUsername": "",
      "verifiedBadge": false,
      "pnl": 1406962.9414736538,
      "vol": 67767069.634251,
      "enriched": {
        "winRate": 71.2,
        "roi": 1.2,
        "totalTrades": 250,
        "wins": 178,
        "losses": 72,
        "categories": [
          "Crypto",
          "Culture",
          "Economics",
          "Finance",
          "Geopolitics",
          "Politics",
          "Sports",
          "Tech",
          "Weather"
        ],
        "sharpe": 0.09,
        "consistency": 70.0,
        "maxDrawdown": -182147.48,
        "sparkline": [
          0.0,
          1715.93,
          4997.06,
          5556.28,
          5556.83,
          11145.29,
          14085.73,
          36188.04,
          36918.72
        ],
        "openPositions": 50,
        "closedPositions": 250,
        "hasCrypto": true,
        "totalPnlFromPositions": 292459.0,
        "totalInvested": 24165910.02,
        "lastTradeTimestamp": 1781044762,
        "tradesInWindow": 50,
        "lastTradeAge": "0.1h ago"
      },
      "scoredRank": 12
    },
    {
      "rank": "19",
      "proxyWallet": "0x9f2fe025f84839ca81dd8e0338892605702d2ca8",
      "userName": "surfandturf",
      "profileImage": "",
      "xUsername": "",
      "verifiedBadge": false,
      "pnl": 4542657.772129348,
      "vol": 65119303.697758995,
      "enriched": {
        "winRate": 52.4,
        "roi": 20.8,
        "totalTrades": 250,
        "wins": 131,
        "losses": 119,
        "categories": [
          "Crypto",
          "Culture",
          "Geopolitics",
          "Sports",
          "Tech",
          "Weather"
        ],
        "sharpe": 0.13,
        "consistency": 69.0,
        "maxDrawdown": -505950.8,
        "sparkline": [
          -12000.02,
          -14828.22,
          -9741.1,
          -9301.0,
          -68650.97,
          -155861.27,
          638379.13,
          639516.22,
          590503.39
        ],
        "openPositions": 2,
        "closedPositions": 250,
        "hasCrypto": true,
        "totalPnlFromPositions": 4449274.75,
        "totalInvested": 21383914.3,
        "lastTradeTimestamp": 1781044524,
        "tradesInWindow": 50,
        "lastTradeAge": "0.2h ago"
      },
      "scoredRank": 13
    },
    {
      "rank": "41",
      "proxyWallet": "0xee00ba338c59557141789b127927a55f5cc5cea1",
      "userName": "S-Works",
      "profileImage": "",
      "xUsername": "",
      "verifiedBadge": false,
      "pnl": 2543876.575566942,
      "vol": 189298614.92037904,
      "enriched": {
        "winRate": 67.6,
        "roi": 2.0,
        "totalTrades": 250,
        "wins": 169,
        "losses": 81,
        "categories": [
          "Crypto",
          "Geopolitics",
          "Politics",
          "Sports",
          "Tech",
          "Weather"
        ],
        "sharpe": 0.07,
        "consistency": 74.0,
        "maxDrawdown": -186019.56,
        "sparkline": [
          1160.57,
          42832.57,
          42828.04,
          91039.0,
          91250.11,
          91356.5,
          98917.21,
          99967.45,
          101098.48
        ],
        "openPositions": 6,
        "closedPositions": 250,
        "hasCrypto": true,
        "totalPnlFromPositions": 583464.72,
        "totalInvested": 28760070.27,
        "lastTradeTimestamp": 1781027763,
        "tradesInWindow": 50,
        "lastTradeAge": "4.8h ago"
      },
      "scoredRank": 14
    },
    {
      "rank": "90",
      "proxyWallet": "0xd218e474776403a330142299f7796e8ba32eb5c9",
      "userName": "cigarettes",
      "profileImage": "",
      "xUsername": "friendlyping",
      "verifiedBadge": false,
      "pnl": 1374124.0368126498,
      "vol": 514024533.19562495,
      "enriched": {
        "winRate": 54.0,
        "roi": 20.3,
        "totalTrades": 250,
        "wins": 135,
        "losses": 115,
        "categories": [
          "Crypto",
          "Culture",
          "Economics",
          "Finance",
          "Geopolitics",
          "Politics",
          "Sports",
          "Tech",
          "Weather"
        ],
        "sharpe": 0.05,
        "consistency": 70.0,
        "maxDrawdown": -3705.03,
        "sparkline": [
          -81.61,
          -73.98,
          -77.08,
          -99.43,
          -3804.45,
          -3793.68,
          -3537.54,
          -3523.61,
          -3523.88
        ],
        "openPositions": 50,
        "closedPositions": 250,
        "hasCrypto": true,
        "totalPnlFromPositions": 27663.74,
        "totalInvested": 136053.76,
        "lastTradeTimestamp": 1781045058,
        "tradesInWindow": 50,
        "lastTradeAge": "0.0h ago"
      },
      "scoredRank": 15
    },
    {
      "rank": "93",
      "proxyWallet": "0x7c3db723f1d4d8cb9c550095203b686cb11e5c6b",
      "userName": "Car",
      "profileImage": "https://polymarket-upload.s3.us-east-2.amazonaws.com/profile-image-501613-aa434e55-7732-41b1-9650-83a9d1d716ef.png",
      "xUsername": "CarOnPolymarket",
      "verifiedBadge": true,
      "pnl": 1332618.8268319746,
      "vol": 165129635.208532,
      "enriched": {
        "winRate": 66.8,
        "roi": 0.3,
        "totalTrades": 250,
        "wins": 167,
        "losses": 83,
        "categories": [
          "Crypto",
          "Culture",
          "Economics",
          "Finance",
          "Geopolitics",
          "Politics",
          "Sports",
          "Tech"
        ],
        "sharpe": 0.04,
        "consistency": 68.0,
        "maxDrawdown": -14615.87,
        "sparkline": [
          3.44,
          -416.04,
          -412.5,
          -391.5,
          -377.37,
          -351.03,
          -60.93,
          34.15,
          32.15
        ],
        "openPositions": 50,
        "closedPositions": 250,
        "hasCrypto": true,
        "totalPnlFromPositions": 24973.81,
        "totalInvested": 7700761.91,
        "lastTradeTimestamp": 1781044993,
        "tradesInWindow": 50,
        "lastTradeAge": "0.1h ago"
      },
      "scoredRank": 16
    },
    {
      "rank": "94",
      "proxyWallet": "0x32ed517a571c01b6e9adecf61ba81ca48ff2f960",
      "userName": "sportmaster777",
      "profileImage": "",
      "xUsername": "",
      "verifiedBadge": false,
      "pnl": 1312250.9237608744,
      "vol": 29105362.423636004,
      "enriched": {
        "winRate": 60.4,
        "roi": 7.6,
        "totalTrades": 250,
        "wins": 151,
        "losses": 99,
        "categories": [
          "Sports"
        ],
        "sharpe": 0.03,
        "consistency": 67.0,
        "maxDrawdown": -5004.24,
        "sparkline": [
          -34.06,
          -37.51,
          -36.01,
          -38.95,
          1515.9,
          1517.9,
          1431.3,
          1523.23,
          1683.48
        ],
        "openPositions": 50,
        "closedPositions": 250,
        "hasCrypto": false,
        "totalPnlFromPositions": 10582.1,
        "totalInvested": 139647.17,
        "lastTradeTimestamp": 1781045020,
        "tradesInWindow": 50,
        "lastTradeAge": "0.1h ago"
      },
      "scoredRank": 17
    },
    {
      "rank": "59",
      "proxyWallet": "0x0c0e270cf879583d6a0142fc817e05b768d0434e",
      "userName": "The Spirit of Ukraine>UMA",
      "profileImage": "",
      "xUsername": "",
      "verifiedBadge": false,
      "pnl": 1968643.7764710458,
      "vol": 114186681.225748,
      "enriched": {
        "winRate": 41.2,
        "roi": 17.8,
        "totalTrades": 250,
        "wins": 103,
        "losses": 147,
        "categories": [
          "Crypto",
          "Economics",
          "Finance",
          "Geopolitics",
          "Politics",
          "Sports",
          "Tech"
        ],
        "sharpe": 0.18,
        "consistency": 64.0,
        "maxDrawdown": -31667.0,
        "sparkline": [
          23015.87,
          29107.18,
          41093.83,
          41114.24,
          40671.62,
          33715.34,
          33546.88,
          33378.42,
          32627.49
        ],
        "openPositions": 50,
        "closedPositions": 250,
        "hasCrypto": true,
        "totalPnlFromPositions": 665731.83,
        "totalInvested": 3746734.61,
        "lastTradeTimestamp": 1781042539,
        "tradesInWindow": 50,
        "lastTradeAge": "0.7h ago"
      },
      "scoredRank": 18
    },
    {
      "rank": "4",
      "proxyWallet": "0x204f72f35326db932158cba6adff0b9a1da95e14",
      "userName": "swisstony",
      "profileImage": "",
      "xUsername": "",
      "verifiedBadge": false,
      "pnl": 9614766.525407812,
      "vol": 868058385.6081313,
      "enriched": {
        "winRate": 56.4,
        "roi": 6.9,
        "totalTrades": 250,
        "wins": 141,
        "losses": 109,
        "categories": [
          "Crypto",
          "Economics",
          "Sports",
          "Tech"
        ],
        "sharpe": 0.05,
        "consistency": 71.0,
        "maxDrawdown": -2423.31,
        "sparkline": [
          88.8,
          -274.03,
          -284.27,
          -225.74,
          -230.94,
          -234.94,
          -239.1,
          743.31,
          783.15
        ],
        "openPositions": 50,
        "closedPositions": 250,
        "hasCrypto": true,
        "totalPnlFromPositions": 15555.46,
        "totalInvested": 224939.75,
        "lastTradeTimestamp": 1781044926,
        "tradesInWindow": 50,
        "lastTradeAge": "0.1h ago"
      },
      "scoredRank": 19
    },
    {
      "rank": "57",
      "proxyWallet": "0xf705fa045201391d9632b7f3cde06a5e24453ca7",
      "userName": "",
      "profileImage": "",
      "xUsername": "",
      "verifiedBadge": false,
      "pnl": 1988598.3081813143,
      "vol": 75010976.66723198,
      "enriched": {
        "winRate": 53.2,
        "roi": 4.7,
        "totalTrades": 250,
        "wins": 133,
        "losses": 117,
        "categories": [
          "Crypto"
        ],
        "sharpe": 0.08,
        "consistency": 66.0,
        "maxDrawdown": -40523.06,
        "sparkline": [
          804.59,
          49875.89,
          40803.48,
          40819.63,
          41879.07,
          42127.59,
          43550.03,
          43558.63,
          39462.95
        ],
        "openPositions": 50,
        "closedPositions": 250,
        "hasCrypto": true,
        "totalPnlFromPositions": 133569.51,
        "totalInvested": 2842356.82,
        "lastTradeTimestamp": 1781044597,
        "tradesInWindow": 50,
        "lastTradeAge": "0.2h ago"
      },
      "scoredRank": 20
    },
    {
      "rank": "21",
      "proxyWallet": "0x2a2c53bd278c04da9962fcf96490e17f3dfb9bc1",
      "userName": "0x2a2C53bD278c04DA9962Fcf96490E17F3DfB9Bc1-1772479215461",
      "profileImage": "",
      "xUsername": "",
      "verifiedBadge": false,
      "pnl": 4263412.117896388,
      "vol": 477114043.56573004,
      "enriched": {
        "winRate": 70.8,
        "roi": 1.9,
        "totalTrades": 250,
        "wins": 177,
        "losses": 73,
        "categories": [
          "Crypto",
          "Geopolitics",
          "Politics",
          "Sports",
          "Weather"
        ],
        "sharpe": 0.16,
        "consistency": 80.0,
        "maxDrawdown": -246210.32,
        "sparkline": [
          202706.17,
          200352.66,
          202358.86,
          202395.91,
          189307.04,
          499575.09,
          502648.02,
          528029.63,
          527989.45
        ],
        "openPositions": 50,
        "closedPositions": 250,
        "hasCrypto": true,
        "totalPnlFromPositions": 2465436.1,
        "totalInvested": 131460355.85,
        "lastTradeTimestamp": 1780995238,
        "tradesInWindow": 3,
        "lastTradeAge": "13.9h ago"
      },
      "scoredRank": 21
    },
    {
      "rank": "89",
      "proxyWallet": "0xbaa2bcb5439e985ce4ccf815b4700027d1b92c73",
      "userName": "denizz",
      "profileImage": "",
      "xUsername": "denizz_poly",
      "verifiedBadge": false,
      "pnl": 1378572.4934739997,
      "vol": 87562158.274542,
      "enriched": {
        "winRate": 57.2,
        "roi": 2.4,
        "totalTrades": 250,
        "wins": 143,
        "losses": 107,
        "categories": [
          "Crypto",
          "Finance",
          "Geopolitics",
          "Politics",
          "Sports",
          "Tech"
        ],
        "sharpe": 0.02,
        "consistency": 60.0,
        "maxDrawdown": -154576.82,
        "sparkline": [
          344.98,
          -4415.65,
          -5455.19,
          13979.09,
          14140.2,
          16850.54,
          16873.44,
          16843.31,
          17683.12
        ],
        "openPositions": 50,
        "closedPositions": 250,
        "hasCrypto": true,
        "totalPnlFromPositions": 216838.42,
        "totalInvested": 8884730.59,
        "lastTradeTimestamp": 1781037259,
        "tradesInWindow": 50,
        "lastTradeAge": "2.2h ago"
      },
      "scoredRank": 22
    },
    {
      "rank": "5",
      "proxyWallet": "0x2005d16a84ceefa912d4e380cd32e7ff827875ea",
      "userName": "RN1",
      "profileImage": "https://polymarket-upload.s3.us-east-2.amazonaws.com/profile-image-1567750-84001aec-310a-470f-9584-67dfcaa61267.png",
      "xUsername": "",
      "verifiedBadge": false,
      "pnl": 9535371.600819157,
      "vol": 625928698.315725,
      "enriched": {
        "winRate": 53.2,
        "roi": 4.9,
        "totalTrades": 250,
        "wins": 133,
        "losses": 117,
        "categories": [
          "Crypto",
          "Culture",
          "Economics",
          "Geopolitics",
          "Politics",
          "Sports",
          "Tech"
        ],
        "sharpe": 0.03,
        "consistency": 49.0,
        "maxDrawdown": -53648.69,
        "sparkline": [
          758.35,
          798.35,
          764.64,
          1717.9,
          2800.29,
          946.55,
          1041.16,
          2352.63,
          -3544.67
        ],
        "openPositions": 50,
        "closedPositions": 250,
        "hasCrypto": true,
        "totalPnlFromPositions": 47522.41,
        "totalInvested": 965870.2,
        "lastTradeTimestamp": 1781044929,
        "tradesInWindow": 50,
        "lastTradeAge": "0.1h ago"
      },
      "scoredRank": 23
    },
    {
      "rank": "71",
      "proxyWallet": "0x7ea571c40408f340c1c8fc8eaacebab53c1bde7b",
      "userName": "Cannae",
      "profileImage": "",
      "xUsername": "",
      "verifiedBadge": false,
      "pnl": 1715432.3563826014,
      "vol": 103920007.512461,
      "enriched": {
        "winRate": 53.2,
        "roi": 2.9,
        "totalTrades": 250,
        "wins": 133,
        "losses": 117,
        "categories": [
          "Crypto",
          "Geopolitics",
          "Sports",
          "Tech"
        ],
        "sharpe": 0.02,
        "consistency": 49.0,
        "maxDrawdown": -4598.7,
        "sparkline": [
          162.43,
          142.01,
          131.15,
          227.64,
          231.64,
          112.63,
          109.1,
          50.8,
          -46.86
        ],
        "openPositions": 50,
        "closedPositions": 250,
        "hasCrypto": true,
        "totalPnlFromPositions": 4001.3,
        "totalInvested": 139710.69,
        "lastTradeTimestamp": 1781044966,
        "tradesInWindow": 50,
        "lastTradeAge": "0.1h ago"
      },
      "scoredRank": 24
    },
    {
      "rank": "92",
      "proxyWallet": "0x9cb990f1862568a63d8601efeebe0304225c32f2",
      "userName": "jtwyslljy",
      "profileImage": "",
      "xUsername": "",
      "verifiedBadge": false,
      "pnl": 1348416.1346518602,
      "vol": 65514864.22347799,
      "enriched": {
        "winRate": 42.0,
        "roi": 10.5,
        "totalTrades": 250,
        "wins": 105,
        "losses": 145,
        "categories": [
          "Crypto",
          "Geopolitics",
          "Sports",
          "Tech"
        ],
        "sharpe": 0.04,
        "consistency": 59.0,
        "maxDrawdown": -57599.9,
        "sparkline": [
          70114.58,
          72614.58,
          85954.58,
          80005.48,
          22405.58,
          17223.97,
          14643.97,
          14643.97,
          -25450.56
        ],
        "openPositions": 6,
        "closedPositions": 250,
        "hasCrypto": true,
        "totalPnlFromPositions": 195932.25,
        "totalInvested": 1857239.44,
        "lastTradeTimestamp": 1781032923,
        "tradesInWindow": 50,
        "lastTradeAge": "3.4h ago"
      },
      "scoredRank": 25
    },
    {
      "rank": "74",
      "proxyWallet": "0x84dbb7103982e3617704a2ed7d5b39691952aeeb",
      "userName": "Soarin22",
      "profileImage": "",
      "xUsername": "Soarin22",
      "verifiedBadge": false,
      "pnl": 1604255.5201245248,
      "vol": 74595161.057098,
      "enriched": {
        "winRate": 51.2,
        "roi": 2.5,
        "totalTrades": 250,
        "wins": 128,
        "losses": 122,
        "categories": [
          "Geopolitics",
          "Sports",
          "Tech",
          "Weather"
        ],
        "sharpe": 0.02,
        "consistency": 49.0,
        "maxDrawdown": -160039.1,
        "sparkline": [
          -0.26,
          -30600.26,
          -26000.05,
          -14998.48,
          -29889.62,
          -23097.06,
          184393.42,
          163482.3,
          167822.43
        ],
        "openPositions": 5,
        "closedPositions": 250,
        "hasCrypto": false,
        "totalPnlFromPositions": 146119.15,
        "totalInvested": 5808943.32,
        "lastTradeTimestamp": 1781021296,
        "tradesInWindow": 50,
        "lastTradeAge": "6.6h ago"
      },
      "scoredRank": 26
    },
    {
      "rank": "76",
      "proxyWallet": "0x000d257d2dc7616feaef4ae0f14600fdf50a758e",
      "userName": "scottilicious",
      "profileImage": "https://polymarket-upload.s3.us-east-2.amazonaws.com/profile-image-583-178de096-51b5-46b0-b1bf-83d0b80ad3d4.jpg",
      "xUsername": "scottonPoly",
      "verifiedBadge": false,
      "pnl": 1598284.0372672917,
      "vol": 67168032.98995999,
      "enriched": {
        "winRate": 75.6,
        "roi": 0.7,
        "totalTrades": 250,
        "wins": 189,
        "losses": 61,
        "categories": [
          "Crypto",
          "Culture",
          "Economics",
          "Finance",
          "Geopolitics",
          "Politics",
          "Sports",
          "Tech"
        ],
        "sharpe": 0.03,
        "consistency": 66.0,
        "maxDrawdown": -55566.11,
        "sparkline": [
          23.7,
          169.44,
          282.24,
          562.33,
          203.01,
          -8977.1,
          -8550.72,
          -8984.36,
          -8820.56
        ],
        "openPositions": 47,
        "closedPositions": 250,
        "hasCrypto": true,
        "totalPnlFromPositions": 57020.03,
        "totalInvested": 7821042.6,
        "lastTradeTimestamp": 1781025217,
        "tradesInWindow": 1,
        "lastTradeAge": "5.6h ago"
      },
      "scoredRank": 27
    },
    {
      "rank": "77",
      "proxyWallet": "0x24c8cf69a0e0a17eee21f69d29752bfa32e823e1",
      "userName": "debased",
      "profileImage": "https://polymarket-upload.s3.us-east-2.amazonaws.com/trump_farmer_b64c6dcd-13e2-4dda-b1c2-0fb46389fb22_1743074825403.png",
      "xUsername": "debased_PM",
      "verifiedBadge": false,
      "pnl": 1580706.540933993,
      "vol": 464792519.3375641,
      "enriched": {
        "winRate": 44.0,
        "roi": 4.5,
        "totalTrades": 250,
        "wins": 110,
        "losses": 140,
        "categories": [
          "Crypto",
          "Economics",
          "Finance",
          "Geopolitics",
          "Politics",
          "Sports",
          "Tech"
        ],
        "sharpe": 0.04,
        "consistency": 52.0,
        "maxDrawdown": -177258.4,
        "sparkline": [
          20472.16,
          17189.14,
          15479.76,
          15545.67,
          -28204.37,
          -29109.01,
          -29240.9,
          -28196.46,
          -28317.56
        ],
        "openPositions": 50,
        "closedPositions": 250,
        "hasCrypto": true,
        "totalPnlFromPositions": 242713.15,
        "totalInvested": 5365683.32,
        "lastTradeTimestamp": 1781045058,
        "tradesInWindow": 50,
        "lastTradeAge": "0.0h ago"
      },
      "scoredRank": 28
    },
    {
      "rank": "37",
      "proxyWallet": "0xfe787d2da716d60e8acff57fb87eb13cd4d10319",
      "userName": "ferrariChampions2026",
      "profileImage": "",
      "xUsername": "",
      "verifiedBadge": false,
      "pnl": 2923124.987089997,
      "vol": 261061571.98590705,
      "enriched": {
        "winRate": 53.6,
        "roi": 1.0,
        "totalTrades": 250,
        "wins": 134,
        "losses": 116,
        "categories": [
          "Crypto",
          "Culture",
          "Economics",
          "Finance",
          "Geopolitics",
          "Politics",
          "Sports",
          "Tech"
        ],
        "sharpe": 0.0,
        "consistency": 32.0,
        "maxDrawdown": -64756.75,
        "sparkline": [
          2143.37,
          1858.17,
          1857.36,
          1623.15,
          1624.15,
          5721.64,
          29652.5,
          29223.25,
          29215.81
        ],
        "openPositions": 50,
        "closedPositions": 250,
        "hasCrypto": true,
        "totalPnlFromPositions": 11646.26,
        "totalInvested": 1125727.37,
        "lastTradeTimestamp": 1781044984,
        "tradesInWindow": 50,
        "lastTradeAge": "0.0h ago"
      },
      "scoredRank": 29
    },
    {
      "rank": "16",
      "proxyWallet": "0x507e52ef684ca2dd91f90a9d26d149dd3288beae",
      "userName": "GamblingIsAllYouNeed",
      "profileImage": "https://polymarket-upload.s3.us-east-2.amazonaws.com/profile-image-4070827-b30f95ed-6835-4ac6-a456-f066d6968f97.png",
      "xUsername": "",
      "verifiedBadge": false,
      "pnl": 4786412.477695955,
      "vol": 436509667.89918995,
      "enriched": {
        "winRate": 52.8,
        "roi": -1.5,
        "totalTrades": 250,
        "wins": 132,
        "losses": 118,
        "categories": [
          "Crypto",
          "Geopolitics",
          "Sports",
          "Tech"
        ],
        "sharpe": -0.01,
        "consistency": 32.0,
        "maxDrawdown": -6242.85,
        "sparkline": [
          0.0,
          27.83,
          94.2,
          927.8,
          1106.36,
          1492.83,
          -4750.01,
          -4749.01,
          -4781.59
        ],
        "openPositions": 44,
        "closedPositions": 250,
        "hasCrypto": true,
        "totalPnlFromPositions": -2688.95,
        "totalInvested": 175649.36,
        "lastTradeTimestamp": 1781044896,
        "tradesInWindow": 50,
        "lastTradeAge": "0.1h ago"
      },
      "scoredRank": 30
    },
    {
      "rank": "99",
      "proxyWallet": "0x93abbc022ce98d6f45d4444b594791cc4b7a9723",
      "userName": "gatorr",
      "profileImage": "",
      "xUsername": "",
      "verifiedBadge": false,
      "pnl": 1221489.0150659978,
      "vol": 52137113.462986,
      "enriched": {
        "winRate": 51.2,
        "roi": -7.2,
        "totalTrades": 250,
        "wins": 128,
        "losses": 122,
        "categories": [
          "Crypto",
          "Culture",
          "Economics",
          "Finance",
          "Geopolitics",
          "Sports",
          "Tech",
          "Weather"
        ],
        "sharpe": -0.06,
        "consistency": 62.0,
        "maxDrawdown": -266209.51,
        "sparkline": [
          454.85,
          -13111.7,
          -17911.7,
          -78440.96,
          -65690.97,
          -51290.97,
          -11133.11,
          -11233.11,
          45845.53
        ],
        "openPositions": 31,
        "closedPositions": 250,
        "hasCrypto": true,
        "totalPnlFromPositions": -639037.44,
        "totalInvested": 8930126.39,
        "lastTradeTimestamp": 1780959472,
        "tradesInWindow": 7,
        "lastTradeAge": "23.8h ago"
      },
      "scoredRank": 31
    },
    {
      "rank": "62",
      "proxyWallet": "0x241f846866c2de4fb67cdb0ca6b963d85e56ef50",
      "userName": "Pestle",
      "profileImage": "https://polymarket-upload.s3.us-east-2.amazonaws.com/profile-image-1793305-ecb4f75a-82a9-4acd-9054-9921831874b4.png",
      "xUsername": "pptpatil",
      "verifiedBadge": false,
      "pnl": 1907480.3952399218,
      "vol": 187152142.48720703,
      "enriched": {
        "winRate": 0.4,
        "roi": -97.9,
        "totalTrades": 250,
        "wins": 1,
        "losses": 249,
        "categories": [
          "Crypto",
          "Culture",
          "Economics",
          "Finance",
          "Geopolitics",
          "Politics",
          "Sports",
          "Tech",
          "Weather"
        ],
        "sharpe": -0.15,
        "consistency": 36.0,
        "maxDrawdown": -6.24,
        "sparkline": [
          0.0,
          -0.01,
          -0.02,
          -0.03,
          -0.04,
          -0.06,
          -0.07,
          -0.09,
          -6.33
        ],
        "openPositions": 50,
        "closedPositions": 250,
        "hasCrypto": true,
        "totalPnlFromPositions": -28.35,
        "totalInvested": 28.95,
        "lastTradeTimestamp": 1781042560,
        "tradesInWindow": 50,
        "lastTradeAge": "0.7h ago"
      },
      "scoredRank": 32
    }
  ]
}